flask_slacksigauth/__init__.py
flask_slacksigauth/version.py
flask_slacksigauth-1.0.10.dist-info/LICENSE
flask_slacksigauth-1.0.10.dist-info/METADATA
flask_slacksigauth-1.0.10.dist-info/WHEEL
flask_slacksigauth-1.0.10.dist-info/top_level.txt
flask_slacksigauth-1.0.10.dist-info/RECORD
