Metadata-Version: 2.1
Name: flask_slacksigauth
Version: 1.0.10
Summary: Python Flask adapter for verifying Slack signatures
Home-page: https://github.com/eaescob/flask-slacksigauth
Author: Emilio Escobar
Author-email: eescobar@gmail.com
License: GNU
License-File: LICENSE
Requires-Dist: flask
Requires-Dist: pyee
Requires-Dist: requests
Requires-Dist: six
